navercafe/__init__.py
navercafe/main.py
navercafe-0.2.1.dist-info/METADATA
navercafe-0.2.1.dist-info/WHEEL
navercafe-0.2.1.dist-info/RECORD
