Metadata-Version: 2.1
Name: navercafe
Version: 0.2.1
Summary: 
Author: Yong Choi
Author-email: ychoi_kr@naver.com
Requires-Python: >=3.10,<4.0
Classifier: Programming Language :: Python :: 3
Classifier: Programming Language :: Python :: 3.10
Classifier: Programming Language :: Python :: 3.11
Classifier: Programming Language :: Python :: 3.12
Requires-Dist: beautifulsoup4 (>=4.12.3,<5.0.0)
Requires-Dist: pandas (>=1.5.2,<2.0.0)
Requires-Dist: pyperclip (>=1.8.2,<2.0.0)
Requires-Dist: selenium (>=4.7.2,<5.0.0)
Requires-Dist: webdriver-manager (>=4.0.1,<5.0.0)
